flask_http2_push.py
flask_http2_push-0.0.3.dist-info/DESCRIPTION.rst
flask_http2_push-0.0.3.dist-info/METADATA
flask_http2_push-0.0.3.dist-info/RECORD
flask_http2_push-0.0.3.dist-info/WHEEL
flask_http2_push-0.0.3.dist-info/metadata.json
flask_http2_push-0.0.3.dist-info/top_level.txt
