Metadata-Version: 2.0
Name: flask-http2-push
Version: 0.0.3
Summary: A Flask extension to add http2 server push to your application.
Home-page: https://github.com/jdaroesti/flask-http2-push
Author: David Aroesti
Author-email: david@aroesti.me
License: MIT
Download-URL: https://github.com/jdaroesti/flask-http2-push/releases/tag/v0.0.3
Keywords: flask http2 push
Platform: any
Classifier: Environment :: Web Environment
Classifier: Intended Audience :: Developers
Classifier: License :: OSI Approved :: BSD License
Classifier: Programming Language :: Python :: 2.7
Classifier: Programming Language :: Python :: 3
Classifier: Operating System :: OS Independent
Classifier: Topic :: Internet :: WWW/HTTP :: Dynamic Content
Classifier: Topic :: Software Development :: Libraries :: Python Modules
Requires-Dist: Flask
